cei/__init__.py
cei/expression_index.py
cei/datasets/ATCC_25922.csv
cei-0.1.1.dist-info/LICENSE
cei-0.1.1.dist-info/METADATA
cei-0.1.1.dist-info/WHEEL
cei-0.1.1.dist-info/top_level.txt
cei-0.1.1.dist-info/RECORD
